Workbook

Sheet Sprints
A1: Plan des sprints
A2: Sprints de 2 semaines. Remplace J par la date réelle quand elle est fixée. Les colonnes D à G se calculent automatiquement depuis le Backlog.
A3: Sprint | B3: Période (J = jour de l'événement) | C3: Objectif du sprint | D3: Nb stories | E3: Points prévus | F3: Points faits | G3: Avancement
A4: Sprint 0 | B4: J-70 → J-57 | C4: Cadrage : équipe, rôles, date, lieu, budget, validation par l'université | D4: =COUNTIF(Backlog!$G$4:$G$200,A4) -> 6 | E4: =SUMIFS(Backlog!$F$4:$F$200,Backlog!$G$4:$G$200,A4) -> 13 | F4: =SUMIFS(Backlog!$F$4:$F$200,Backlog!$G$4:$G$200,A4,Backlog!$H$4:$H$200,"Fait") -> 2 | G4: =IF(E4=0,0,F4/E4) -> 0.15384615
A5: Sprint 1 | B5: J-56 → J-43 | C5: Programme défini, intervenants contactés, salles réservées | D5: =COUNTIF(Backlog!$G$4:$G$200,A5) -> 5 | E5: =SUMIFS(Backlog!$F$4:$F$200,Backlog!$G$4:$G$200,A5) -> 18 | F5: =SUMIFS(Backlog!$F$4:$F$200,Backlog!$G$4:$G$200,A5,Backlog!$H$4:$H$200,"Fait") -> 0 | G5: =IF(E5=0,0,F5/E5) -> 0
A6: Sprint 2 | B6: J-42 → J-29 | C6: Communication lancée, inscriptions ouvertes, CTF en conception | D6: =COUNTIF(Backlog!$G$4:$G$200,A6) -> 10 | E6: =SUMIFS(Backlog!$F$4:$F$200,Backlog!$G$4:$G$200,A6) -> 42 | F6: =SUMIFS(Backlog!$F$4:$F$200,Backlog!$G$4:$G$200,A6,Backlog!$H$4:$H$200,"Fait") -> 0 | G6: =IF(E6=0,0,F6/E6) -> 0
A7: Sprint 3 | B7: J-28 → J-15 | C7: Contenus prêts : CTF testé, ateliers rédigés, partenaires confirmés | D7: =COUNTIF(Backlog!$G$4:$G$200,A7) -> 11 | E7: =SUMIFS(Backlog!$F$4:$F$200,Backlog!$G$4:$G$200,A7) -> 31 | F7: =SUMIFS(Backlog!$F$4:$F$200,Backlog!$G$4:$G$200,A7,Backlog!$H$4:$H$200,"Fait") -> 0 | G7: =IF(E7=0,0,F7/E7) -> 0
A8: Sprint 4 | B8: J-14 → J-1 | C8: Répétitions, logistique finale, relances, go/no-go | D8: =COUNTIF(Backlog!$G$4:$G$200,A8) -> 5 | E8: =SUMIFS(Backlog!$F$4:$F$200,Backlog!$G$4:$G$200,A8) -> 9 | F8: =SUMIFS(Backlog!$F$4:$F$200,Backlog!$G$4:$G$200,A8,Backlog!$H$4:$H$200,"Fait") -> 0 | G8: =IF(E8=0,0,F8/E8) -> 0
A9: Jour J | B9: J | C9: Déroulé de l'événement, accueil, animation, captation | D9: =COUNTIF(Backlog!$G$4:$G$200,A9) -> 2 | E9: =SUMIFS(Backlog!$F$4:$F$200,Backlog!$G$4:$G$200,A9) -> 4 | F9: =SUMIFS(Backlog!$F$4:$F$200,Backlog!$G$4:$G$200,A9,Backlog!$H$4:$H$200,"Fait") -> 0 | G9: =IF(E9=0,0,F9/E9) -> 0
A10: Post-event | B10: J+1 → J+14 | C10: Bilan, remerciements, rétrospective finale, archivage | D10: =COUNTIF(Backlog!$G$4:$G$200,A10) -> 3 | E10: =SUMIFS(Backlog!$F$4:$F$200,Backlog!$G$4:$G$200,A10) -> 4 | F10: =SUMIFS(Backlog!$F$4:$F$200,Backlog!$G$4:$G$200,A10,Backlog!$H$4:$H$200,"Fait") -> 0 | G10: =IF(E10=0,0,F10/E10) -> 0
A11: TOTAL | D11: =SUM(D4:D10) -> 42 | E11: =SUM(E4:E10) -> 121 | F11: =SUM(F4:F10) -> 2 | G11: =IF(E11=0,0,F11/E11) -> 0.016528926

Sheet Backlog
A1: SECURITY DAY LYON 2 — Product Backlog
A2: Cases jaunes = à remplir/mettre à jour (Statut, Responsable, Sprint). Priorité MoSCoW : Must / Should / Could / Won't. Points en suite de Fibonacci (1, 2, 3, 5, 8, 13).
A3: ID | B3: Epic | C3: User story | D3: Critères d'acceptation | E3: Priorité | F3: Points | G3: Sprint | H3: Statut | I3: Responsable
A4: CAD-01 | B4: Cadrage & gouvernance | C4: En tant qu'organisateur, je veux constituer l'équipe et attribuer les rôles (PO, SM, pôles) afin que chacun sache ce qu'il porte. | D4: Liste de l'équipe validée ; un référent par pôle ; rôles publiés dans l'onglet Équipe. | E4: Must | F4: 2 | G4: Sprint 0 | H4: Fait | I4: Chasky (SM)
A5: CAD-02 | B5: Cadrage & gouvernance | C5: En tant que Product Owner, je veux définir la vision et les objectifs de l'événement afin d'aligner l'équipe. | D5: Vision en 3 phrases ; 3 objectifs mesurables (nb participants, nb ateliers, satisfaction). | E5: Must | F5: 2 | G5: Sprint 0 | H5: À faire
A6: CAD-03 | B6: Cadrage & gouvernance | C6: En tant qu'équipe, je veux obtenir la validation de l'université (responsable du master / administration) afin d'organiser l'événement officiellement. | D6: Accord écrit reçu ; interlocuteur administratif identifié. | E6: Must | F6: 3 | G6: Sprint 0 | H6: À faire
A7: CAD-04 | B7: Cadrage & gouvernance | C7: En tant qu'équipe, je veux fixer la date et le format (journée / demi-journée) afin de lancer la planification. | D7: Date validée sans conflit d'examens ; format arrêté. | E7: Must | F7: 2 | G7: Sprint 0 | H7: À faire
A8: CAD-05 | B8: Cadrage & gouvernance | C8: En tant que SM, je veux mettre en place l'outil de suivi (Trello/Jira/Notion) et le canal d'équipe afin de piloter les sprints. | D8: Board créé avec ce backlog ; canal Discord/WhatsApp actif ; rituels planifiés. | E8: Must | F8: 1 | G8: Sprint 0 | H8: À faire | I8: Chasky (SM)
A9: PART-01 | B9: Partenaires & budget | C9: En tant que trésorier, je veux établir un budget prévisionnel afin de connaître nos besoins de financement. | D9: Budget recettes/dépenses ; postes : impression, restauration, lots, matériel. | E9: Must | F9: 3 | G9: Sprint 0 | H9: À faire
A10: PRG-01 | B10: Programme | C10: En tant que PO, je veux définir le programme horaire de la journée afin de caler ateliers, talks et CTF. | D10: Planning horaire validé ; pas de chevauchement de salles. | E10: Must | F10: 3 | G10: Sprint 1 | H10: À faire
A11: CONF-01 | B11: Conférences & table ronde | C11: En tant que pôle programme, je veux lister et contacter des intervenants (pros, chercheurs, anciens OPSIE) afin de remplir les créneaux de conférence. | D11: Liste de 8+ contacts ; mails envoyés ; relance à J+7. | E11: Must | F11: 5 | G11: Sprint 1 | H11: À faire
A12: CONF-02 | B12: Conférences & table ronde | C12: En tant que pôle programme, je veux confirmer les intervenants et leurs sujets afin de publier le programme. | D12: Confirmation écrite de chaque intervenant ; titre et résumé reçus. | E12: Must | F12: 3 | G12: Sprint 2 | H12: À faire
A13: CONF-03 | B13: Conférences & table ronde | C13: En tant qu'animateur, je veux préparer la table ronde (thème métiers/stages, panélistes, questions) afin d'avoir un débat fluide. | D13: 3-4 panélistes ; 10 questions préparées ; modérateur désigné. | E13: Should | F13: 3 | G13: Sprint 3 | H13: À faire
A14: LOG-01 | B14: Logistique & technique | C14: En tant que pôle logistique, je veux réserver les salles (amphi + salles TP) afin d'accueillir chaque activité. | D14: Réservations confirmées par écrit ; capacités adaptées. | E14: Must | F14: 3 | G14: Sprint 1 | H14: À faire
A15: LOG-02 | B15: Logistique & technique | C15: En tant que pôle technique, je veux vérifier réseau, postes, vidéoprojecteurs et prises afin d'éviter les pannes le jour J. | D15: Check-list technique signée pour chaque salle ; accès Wi-Fi invités obtenu. | E15: Must | F15: 3 | G15: Sprint 3 | H15: À faire
A16: LOG-03 | B16: Logistique & technique | C16: En tant que pôle technique, je veux un réseau isolé (VLAN/lab) pour le CTF afin que les attaques restent confinées. | D16: Environnement isolé validé avec la DSI ; aucune exposition au réseau de l'université. | E16: Must | F16: 5 | G16: Sprint 2 | H16: À faire
A17: CTF-01 | B17: CTF | C17: En tant que concepteur CTF, je veux définir les catégories et le niveau des challenges afin de convenir aux débutants comme aux confirmés. | D17: Catégories : web, crypto, forensic, reverse, OSINT ; 3 niveaux de difficulté. | E17: Must | F17: 2 | G17: Sprint 1 | H17: À faire
A18: CTF-02 | B18: CTF | C18: En tant que concepteur CTF, je veux créer les challenges et leurs flags afin de disposer d'un CTF complet. | D18: 20+ challenges ; write-up interne pour chacun. | E18: Must | F18: 13 | G18: Sprint 2 | H18: À faire
A19: CTF-03 | B19: CTF | C19: En tant que pôle technique, je veux déployer la plateforme (CTFd) avec scoreboard afin de gérer équipes et scores. | D19: CTFd en ligne sur l'environnement isolé ; comptes de test OK. | E19: Must | F19: 5 | G19: Sprint 2 | H19: À faire
A20: CTF-04 | B20: CTF | C20: En tant qu'équipe, je veux faire un bêta-test du CTF afin de corriger bugs et flags cassés. | D20: Chaque challenge résolu par au moins 1 testeur ; bugs corrigés. | E20: Must | F20: 5 | G20: Sprint 3 | H20: À faire
... A38: LOG-05 | B38: Logistique & technique | C38: En tant que pôle logistique, je veux préparer la signalétique et les badges afin d'orienter les participants. | D38: Fléchage imprimé ; badges orga/intervenants/participants. | E38: Could | F38: 2 | G38: Sprint 4 | H38: À faire
A39: JJ-01 | B39: Jour J | C39: En tant que SM, je veux un planning minute par minute du jour J avec les responsables afin que tout le monde sache où être. | D39: Run-sheet partagée ; un responsable par créneau et par salle. | E39: Must | F39: 3 | G39: Sprint 4 | H39: À faire | I39: Chasky (SM)
A40: JJ-02 | B40: Jour J | C40: En tant qu'équipe, je veux faire un go/no-go à J-2 afin de valider que tout est prêt. | D40: Revue de la check-list ; points bloquants traités ou plan B. | E40: Must | F40: 1 | G40: Sprint 4 | H40: À faire | I40: Chasky (SM)
A41: JJ-03 | B41: Jour J | C41: En tant que participant, je veux être accueilli et orienté afin de trouver rapidement mes activités. | D41: Stand d'accueil ; pointage des inscrits ; plan des salles. | E41: Must | F41: 2 | G41: Jour J | H41: À faire
A42: JJ-04 | B42: Jour J | C42: En tant qu'équipe, je veux capter photos/vidéos afin d'alimenter la com post-événement. | D42: Photographe désigné ; droit à l'image signalé à l'entrée. | E42: Could | F42: 2 | G42: Jour J | H42: À faire
A43: POST-01 | B43: Post-événement | C43: En tant qu'organisateur, je veux envoyer un questionnaire de satisfaction afin de mesurer la réussite. | D43: Questionnaire envoyé à J+1 ; taux de réponse suivi. | E43: Should | F43: 1 | G43: Post-event | H43: À faire
A44: POST-02 | B44: Post-événement | C44: En tant que pôle com, je veux remercier intervenants, sponsors et participants afin de préparer les prochaines éditions. | D44: Mails de remerciement ; post récap avec photos. | E44: Should | F44: 1 | G44: Post-event | H44: À faire
A45: POST-03 | B45: Post-événement | C45: En tant que SM, je veux animer la rétrospective finale et produire un bilan afin de capitaliser pour l'édition suivante. | D45: Rétro tenue ; bilan chiffré (participants, budget, satisfaction) archivé. | E45: Must | F45: 2 | G45: Post-event | H45: À faire | I45: Chasky (SM)

Sheet Epics
A1: Vue par Epic
A2: Calcul automatique depuis le Backlog.
A3: Epic | B3: Nb stories | C3: Points totaux | D3: Points faits | E3: Avancement | F3: Stories bloquées
A4: Cadrage & gouvernance | B4: =COUNTIF(Backlog!$B$4:$B$200,A4) -> 5 | C4: =SUMIFS(Backlog!$F$4:$F$200,Backlog!$B$4:$B$200,A4) -> 10 | D4: =SUMIFS(Backlog!$F$4:$F$200,Backlog!$B$4:$B$200,A4,Backlog!$H$4:$H$200,"Fait") -> 2 | E4: =IF(C4=0,0,D4/C4) -> 0.2 | F4: =COUNTIFS(Backlog!$B$4:$B$200,A4,Backlog!$H$4:$H$200,"Bloqué") -> 0
A5: Programme | B5: =COUNTIF(Backlog!$B$4:$B$200,A5) -> 1 | C5: =SUMIFS(Backlog!$F$4:$F$200,Backlog!$B$4:$B$200,A5) -> 3 | D5: =SUMIFS(Backlog!$F$4:$F$200,Backlog!$B$4:$B$200,A5,Backlog!$H$4:$H$200,"Fait") -> 0 | E5: =IF(C5=0,0,D5/C5) -> 0 | F5: =COUNTIFS(Backlog!$B$4:$B$200,A5,Backlog!$H$4:$H$200,"Bloqué") -> 0
A6: CTF | B6: =COUNTIF(Backlog!$B$4:$B$200,A6) -> 6 | C6: =SUMIFS(Backlog!$F$4:$F$200,Backlog!$B$4:$B$200,A6) -> 28 | D6: =SUMIFS(Backlog!$F$4:$F$200,Backlog!$B$4:$B$200,A6,Backlog!$H$4:$H$200,"Fait") -> 0 | E6: =IF(C6=0,0,D6/C6) -> 0 | F6: =COUNTIFS(Backlog!$B$4:$B$200,A6,Backlog!$H$4:$H$200,"Bloqué") -> 0
A7: Ateliers crypto | B7: =COUNTIF(Backlog!$B$4:$B$200,A7) -> 3 | C7: =SUMIFS(Backlog!$F$4:$F$200,Backlog!$B$4:$B$200,A7) -> 12 | D7: =SUMIFS(Backlog!$F$4:$F$200,Backlog!$B$4:$B$200,A7,Backlog!$H$4:$H$200,"Fait") -> 0 | E7: =IF(C7=0,0,D7/C7) -> 0 | F7: =COUNTIFS(Backlog!$B$4:$B$200,A7,Backlog!$H$4:$H$200,"Bloqué") -> 0
A8: Conférences & table ronde | B8: =COUNTIF(Backlog!$B$4:$B$200,A8) -> 3 | C8: =SUMIFS(Backlog!$F$4:$F$200,Backlog!$B$4:$B$200,A8) -> 11 | D8: =SUMIFS(Backlog!$F$4:$F$200,Backlog!$B$4:$B$200,A8,Backlog!$H$4:$H$200,"Fait") -> 0 | E8: =IF(C8=0,0,D8/C8) -> 0 | F8: =COUNTIFS(Backlog!$B$4:$B$200,A8,Backlog!$H$4:$H$200,"Bloqué") -> 0
A9: Communication | B9: =COUNTIF(Backlog!$B$4:$B$200,A9) -> 5 | C9: =SUMIFS(Backlog!$F$4:$F$200,Backlog!$B$4:$B$200,A9) -> 11 | D9: =SUMIFS(Backlog!$F$4:$F$200,Backlog!$B$4:$B$200,A9,Backlog!$H$4:$H$200,"Fait") -> 0 | E9: =IF(C9=0,0,D9/C9) -> 0 | F9: =COUNTIFS(Backlog!$B$4:$B$200,A9,Backlog!$H$4:$H$200,"Bloqué") -> 0
A10: Logistique & technique | B10: =COUNTIF(Backlog!$B$4:$B$200,A10) -> 5 | C10: =SUMIFS(Backlog!$F$4:$F$200,Backlog!$B$4:$B$200,A10) -> 16 | D10: =SUMIFS(Backlog!$F$4:$F$200,Backlog!$B$4:$B$200,A10,Backlog!$H$4:$H$200,"Fait") -> 0 | E10: =IF(C10=0,0,D10/C10) -> 0 | F10: =COUNTIFS(Backlog!$B$4:$B$200,A10,Backlog!$H$4:$H$200,"Bloqué") -> 0
A11: Partenaires & budget | B11: =COUNTIF(Backlog!$B$4:$B$200,A11) -> 3 | C11: =SUMIFS(Backlog!$F$4:$F$200,Backlog!$B$4:$B$200,A11) -> 11 | D11: =SUMIFS(Backlog!$F$4:$F$200,Backlog!$B$4:$B$200,A11,Backlog!$H$4:$H$200,"Fait") -> 0 | E11: =IF(C11=0,0,D11/C11) -> 0 | F11: =COUNTIFS(Backlog!$B$4:$B$200,A11,Backlog!$H$4:$H$200,"Bloqué") -> 0
A12: Inscriptions & participants | B12: =COUNTIF(Backlog!$B$4:$B$200,A12) -> 4 | C12: =SUMIFS(Backlog!$F$4:$F$200,Backlog!$B$4:$B$200,A12) -> 7 | D12: =SUMIFS(Backlog!$F$4:$F$200,Backlog!$B$4:$B$200,A12,Backlog!$H$4:$H$200,"Fait") -> 0 | E12: =IF(C12=0,0,D12/C12) -> 0 | F12: =COUNTIFS(Backlog!$B$4:$B$200,A12,Backlog!$H$4:$H$200,"Bloqué") -> 0
A13: Jour J | B13: =COUNTIF(Backlog!$B$4:$B$200,A13) -> 4 | C13: =SUMIFS(Backlog!$F$4:$F$200,Backlog!$B$4:$B$200,A13) -> 8 | D13: =SUMIFS(Backlog!$F$4:$F$200,Backlog!$B$4:$B$200,A13,Backlog!$H$4:$H$200,"Fait") -> 0 | E13: =IF(C13=0,0,D13/C13) -> 0 | F13: =COUNTIFS(Backlog!$B$4:$B$200,A13,Backlog!$H$4:$H$200,"Bloqué") -> 0
A14: Post-événement | B14: =COUNTIF(Backlog!$B$4:$B$200,A14) -> 3 | C14: =SUMIFS(Backlog!$F$4:$F$200,Backlog!$B$4:$B$200,A14) -> 4 | D14: =SUMIFS(Backlog!$F$4:$F$200,Backlog!$B$4:$B$200,A14,Backlog!$H$4:$H$200,"Fait") -> 0 | E14: =IF(C14=0,0,D14/C14) -> 0 | F14: =COUNTIFS(Backlog!$B$4:$B$200,A14,Backlog!$H$4:$H$200,"Bloqué") -> 0

Sheet Équipe
A1: Équipe & rôles
A2: Complète la colonne Nom (cases jaunes).
A3: Rôle / Pôle | B3: Nom | C3: Responsabilités | D3: Epics portés
A4: Scrum Master | B4: Chasky | C4: Anime les rituels, lève les blocages, suit l'avancement et la run-sheet du jour J | D4: Cadrage & gouvernance, Jour J, Post-événement
A5: Product Owner | C5: Porte la vision, priorise le backlog, valide les livrables (sprint review) | D5: Cadrage & gouvernance, Programme
A6: Pôle Programme | C6: Intervenants, conférences, table ronde | D6: Programme, Conférences & table ronde
A7: Pôle CTF | C7: Conception des challenges, plateforme, bêta-test, règlement | D7: CTF
A8: Pôle Ateliers | C8: Ateliers crypto : contenus, supports, animation | D8: Ateliers crypto
A9: Pôle Communication | C9: Poster, réseaux sociaux, mailings, affichage, photos | D9: Communication
A10: Pôle Logistique & Technique | C10: Salles, réseau isolé, matériel, restauration, signalétique | D10: Logistique & technique
A11: Pôle Partenariats & Budget | C11: Sponsors, budget, lots | D11: Partenaires & budget
A12: Pôle Inscriptions | C12: Formulaire, suivi, rappels, RGPD, accueil | D12: Inscriptions & participants

Sheet Cérémonies
A1: Rituels Scrum adaptés à l'équipe
A2: Format léger compatible avec les cours : daily asynchrone, cérémonies en visio ou après 17h.
A3: Cérémonie | B3: Fréquence | C3: Durée | D3: Participants | E3: Objectif / format
A4: Sprint Planning | B4: Début de chaque sprint | C4: 45 min | D4: Toute l'équipe | E4: Choisir les stories du sprint, fixer l'objectif, répartir les responsables
A5: Daily (asynchrone) | B5: Chaque jour ouvré | C5: 5 min | D5: Toute l'équipe | E5: Message sur le canal : fait hier / prévu aujourd'hui / blocages
A6: Point hebdo | B6: 1 fois par semaine | C6: 20 min | D6: Toute l'équipe | E6: Synchro rapide en visio, traitement des blocages
A7: Sprint Review | B7: Fin de chaque sprint | C7: 30 min | D7: Équipe + PO (+ responsable du master si besoin) | E7: Montrer ce qui est fini (poster, CTF, programme…) et récolter les retours
A8: Rétrospective | B8: Fin de chaque sprint | C8: 30 min | D8: Toute l'équipe | E8: Ce qui marche / ce qui coince / 1 à 2 actions d'amélioration
A9: Backlog Refinement | B9: Milieu de sprint | C9: 30 min | D9: PO + SM + référents de pôle | E9: Affiner et estimer les stories du sprint suivant
A10: Go / No-Go | B10: J-2 | C10: 30 min | D10: Toute l'équipe | E10: Revue finale de la check-list, activation des plans B
A11: Rétro finale | B11: J+7 | C11: 1 h | D11: Toute l'équipe | E11: Bilan global et recommandations pour la prochaine édition

Sheet Risques
A1: Registre des risques
A2: Probabilité et impact : Faible / Moyen / Élevé. Revoir à chaque rétrospective.
A3: Risque | B3: Probabilité | C3: Impact | D3: Plan de mitigation | E3: Responsable
A4: Pas de validation de l'université ou délais administratifs | B4: Moyen | C4: Élevé | D4: Demander l'accord dès le Sprint 0 ; passer par le responsable du master
A5: Intervenants qui se désistent | B5: Moyen | C5: Moyen | D5: Garder 2 intervenants de réserve ; prévoir un talk interne de secours
A6: Faible nombre d'inscrits | B6: Moyen | C6: Élevé | D6: Com étalée sur 4 semaines ; relais par les responsables de formation ; rappels
A7: Panne réseau / plateforme CTF | B7: Faible | C7: Élevé | D7: Environnement testé en amont ; version hors-ligne des challenges ; technicien dédié
A8: Attaques qui débordent du périmètre CTF | B8: Faible | C8: Élevé | D8: Réseau isolé validé avec la DSI ; règlement signé ; surveillance pendant l'épreuve
A9: Budget insuffisant | B9: Moyen | C9: Moyen | D9: Sponsors dès le Sprint 1 ; lister les dépenses non essentielles à couper
A10: Équipe surchargée par les cours et examens | B10: Élevé | C10: Moyen | D10: Sprints réalistes, daily asynchrone, marge de 2 semaines avant J
